django_polls_gs377209/__init__.py
django_polls_gs377209/admin.py
django_polls_gs377209/apps.py
django_polls_gs377209/models.py
django_polls_gs377209/tests.py
django_polls_gs377209/urls.py
django_polls_gs377209/views.py
django_polls_gs377209/migrations/0001_initial.py
django_polls_gs377209/migrations/__init__.py
django_polls_gs377209/static/polls/style.css
django_polls_gs377209/static/polls/images/background.jpg
django_polls_gs377209/templates/polls/detail.html
django_polls_gs377209/templates/polls/index.html
django_polls_gs377209/templates/polls/results.html
django_polls_gs377209-0.0.5.dist-info/licenses/LICENSE
django_polls_gs377209-0.0.5.dist-info/METADATA
django_polls_gs377209-0.0.5.dist-info/WHEEL
django_polls_gs377209-0.0.5.dist-info/top_level.txt
django_polls_gs377209-0.0.5.dist-info/RECORD
